xsec/__init__.py
xsec/evaluation.py
xsec/features.py
xsec/gploader.py
xsec/kernels.py
xsec/parameters.py
xsec/utils.py
xsec-1.0.2.data/scripts/xsec
xsec-1.0.2.data/scripts/xsec-download-gprocs
xsec-1.0.2.data/scripts/xsec-test
xsec-1.0.2.dist-info/LICENSE
xsec-1.0.2.dist-info/METADATA
xsec-1.0.2.dist-info/WHEEL
xsec-1.0.2.dist-info/top_level.txt
xsec-1.0.2.dist-info/RECORD
